[
  {
    "outputFileName": "Scripts/Login.min.js",
    "inputFiles": [
      "Scripts/Login.js"
    ]
  },
  {
    "outputFileName": "Scripts/Devices.min.js",
    "inputFiles": [
      "Scripts/Devices.js"
    ]
  },
  {
    "outputFileName": "Scripts/NavigateLAN.min.js",
    "inputFiles": [
      "Scripts/NavigateLAN.js"
    ]
  },
  {
    "outputFileName": "Scripts/NavigateEthernet.min.js",
    "inputFiles": [
      "Scripts/NavigateEthernet.js"
    ]
  },
  {
    "outputFileName": "Scripts/DeviceInfo.min.js",
    "inputFiles": [
      "Scripts/DeviceInfo.js"
    ]
  }
]
